__init__.py
voxel_world.py
voxel_world-0.2.1.dist-info/LICENSE
voxel_world-0.2.1.dist-info/METADATA
voxel_world-0.2.1.dist-info/WHEEL
voxel_world-0.2.1.dist-info/top_level.txt
voxel_world-0.2.1.dist-info/RECORD
