Metadata-Version: 2.1
Name: voxel_world
Version: 0.2.1
Summary: Delicious Voxel worlds in Python
Author-email: JP <jack.parmer@pm.me>
Requires-Python: >=3.7
License-File: LICENSE
Requires-Dist: vnoise
Requires-Dist: numpy
Requires-Dist: pillow
Requires-Dist: matplotlib
Requires-Dist: IPython
